tests/__init__.py
tests/common.py
xjsonrpc/__about__.py
xjsonrpc/__init__.py
xjsonrpc/client/__init__.py
xjsonrpc/client/client.py
xjsonrpc/client/tracer.py
xjsonrpc/client/backend/__init__.py
xjsonrpc/client/backend/aio_pika.py
xjsonrpc/client/backend/aiohttp.py
xjsonrpc/client/backend/httpx.py
xjsonrpc/client/backend/kombu.py
xjsonrpc/client/backend/requests.py
xjsonrpc/client/integrations/__init__.py
xjsonrpc/client/integrations/pytest.py
xjsonrpc/common/__init__.py
xjsonrpc/common/common.py
xjsonrpc/common/exceptions.py
xjsonrpc/common/generators.py
xjsonrpc/common/v10.py
xjsonrpc/common/v20.py
xjsonrpc/server/__init__.py
xjsonrpc/server/dispatcher.py
xjsonrpc/server/utils.py
xjsonrpc/server/integration/__init__.py
xjsonrpc/server/integration/aio_pika.py
xjsonrpc/server/integration/aiohttp.py
xjsonrpc/server/integration/flask.py
xjsonrpc/server/integration/kombu.py
xjsonrpc/server/integration/starlette.py
xjsonrpc/server/integration/werkzeug.py
xjsonrpc/server/integration/django/__init__.py
xjsonrpc/server/integration/django/apps.py
xjsonrpc/server/integration/django/sites.py
xjsonrpc/server/integration/django/urls.py
xjsonrpc/server/specs/__init__.py
xjsonrpc/server/specs/openapi.py
xjsonrpc/server/specs/openrpc.py
xjsonrpc/server/specs/extractors/__init__.py
xjsonrpc/server/specs/extractors/docstring.py
xjsonrpc/server/specs/extractors/pydantic.py
xjsonrpc/server/validators/__init__.py
xjsonrpc/server/validators/base.py
xjsonrpc/server/validators/jsonschema.py
xjsonrpc/server/validators/pydantic.py
xjsonrpc-1.4.3.dist-info/LICENSE
xjsonrpc-1.4.3.dist-info/METADATA
xjsonrpc-1.4.3.dist-info/WHEEL
xjsonrpc-1.4.3.dist-info/entry_points.txt
xjsonrpc-1.4.3.dist-info/top_level.txt
xjsonrpc-1.4.3.dist-info/RECORD
