Metadata-Version: 2.1
Name: xjsonrpc
Version: 1.4.3
Summary: Extensible JSON-RPC library
Home-page: https://github.com/bernhardkaindl/xjsonrpc
Author: Dmitry Pershin, Bernhard Kaindl
Author-email: bernhardkaindl7@gmail.com
License: Public Domain License
Project-URL: Documentation, https://xjsonrpc.readthedocs.io/en/latest/
Project-URL: Source, https://github.com/bernhardkaindl/xjsonrpc
Keywords: json-rpc,rpc,jsonrpc-client,jsonrpc-server,requests,aiohttp,flask,httpx,aio-pika,kombu,openapi,openrpc,starlette,django
Platform: UNKNOWN
Classifier: Development Status :: 4 - Beta
Classifier: Intended Audience :: Developers
Classifier: Natural Language :: English
Classifier: License :: Public Domain
Classifier: Programming Language :: Python
Classifier: Programming Language :: Python :: 3.6
Classifier: Programming Language :: Python :: 3.7
Classifier: Programming Language :: Python :: 3.8
Classifier: Programming Language :: Python :: 3.9
Classifier: Programming Language :: Python :: 3.10
Requires-Python: >=3.6
License-File: LICENSE
Provides-Extra: aio-pika
Requires-Dist: aio-pika (~=7.0) ; extra == 'aio-pika'
Provides-Extra: aiohttp
Requires-Dist: aiohttp (~=3.0) ; extra == 'aiohttp'
Provides-Extra: django
Requires-Dist: django (~=3.0) ; extra == 'django'
Provides-Extra: docstring-parser
Requires-Dist: docstring-parser (~=0.0) ; extra == 'docstring-parser'
Provides-Extra: flask
Requires-Dist: flask (~=2.0) ; extra == 'flask'
Provides-Extra: httpx
Requires-Dist: requests (~=0.0) ; extra == 'httpx'
Provides-Extra: jsonschema
Requires-Dist: jsonschema (~=3.0) ; extra == 'jsonschema'
Provides-Extra: kombu
Requires-Dist: kombu (~=5.0) ; extra == 'kombu'
Provides-Extra: openapi-ui-bundles
Requires-Dist: openapi-ui-bundles (~=0.0) ; extra == 'openapi-ui-bundles'
Provides-Extra: pydantic
Requires-Dist: pydantic (~=1.8.0) ; extra == 'pydantic'
Provides-Extra: requests
Requires-Dist: requests (~=2.0) ; extra == 'requests'
Provides-Extra: starlette
Requires-Dist: starlette (~=0.12.0) ; extra == 'starlette'
Requires-Dist: aiofiles (~=0.7) ; extra == 'starlette'
Provides-Extra: test
Requires-Dist: aioresponses (~=0.0) ; extra == 'test'
Requires-Dist: docstring-parser (~=0.0) ; extra == 'test'
Requires-Dist: flask (~=2.0) ; extra == 'test'
Requires-Dist: jsonschema (~=3.0) ; extra == 'test'
Requires-Dist: pytest (~=6.0) ; extra == 'test'
Requires-Dist: pytest-aiohttp (~=0.0) ; extra == 'test'
Requires-Dist: pytest-mock (~=3.0) ; extra == 'test'
Requires-Dist: responses (~=0.0) ; extra == 'test'
Requires-Dist: respx (~=0.0) ; extra == 'test'
Requires-Dist: pydantic (~=1.8.0) ; extra == 'test'
Requires-Dist: werkzeug (~=2.0) ; extra == 'test'
Requires-Dist: openapi-ui-bundles (~=0.0) ; extra == 'test'
